openwebui_client/__init__.py
openwebui_client/_version.py
openwebui_client/client.py
openwebui_client/completions.py
openwebui_client/files.py
openwebui_client/models.py
openwebui_client/py.typed
openwebui_client/tools.py
openwebui_client-0.3.2.dist-info/licenses/LICENSE
openwebui_client-0.3.2.dist-info/METADATA
openwebui_client-0.3.2.dist-info/WHEEL
openwebui_client-0.3.2.dist-info/top_level.txt
openwebui_client-0.3.2.dist-info/RECORD
